ipythond3sankey
